five.customerize-3.0.0-py3.12-nspkg.pth
five/customerize/__init__.py
five/customerize/browser.py
five/customerize/browser.txt
five/customerize/configure.zcml
five/customerize/customerize.txt
five/customerize/customize.pt
five/customerize/interfaces.py
five/customerize/registrations.pt
five/customerize/tests.py
five/customerize/testviewtemplate.pt
five/customerize/utils.py
five/customerize/version.txt
five/customerize/zpt.py
five/customerize/zpt.txt
five/customerize/zptviews.pt
five.customerize-3.0.0.dist-info/LICENSE.txt
five.customerize-3.0.0.dist-info/METADATA
five.customerize-3.0.0.dist-info/WHEEL
five.customerize-3.0.0.dist-info/namespace_packages.txt
five.customerize-3.0.0.dist-info/top_level.txt
five.customerize-3.0.0.dist-info/RECORD
