Metadata-Version: 2.1
Name: five.customerize
Version: 3.0.0
Summary: TTW customization of template-based Zope browser views
Home-page: https://github.com/zopefoundation/five.customerize
Author: Zope Foundation and Contributors
Author-email: zope-dev@zope.dev
License: ZPL 2.1
Project-URL: Issue Tracker, https://github.com/zopefoundation/five.customerize/issues
Project-URL: Sources, https://github.com/zopefoundation/five.customerize
Keywords: zope views templates customization ttw
Platform: Any
Classifier: Development Status :: 5 - Production/Stable
Classifier: Environment :: Web Environment
Classifier: Framework :: Zope :: 4
Classifier: Framework :: Zope :: 5
Classifier: License :: OSI Approved :: Zope Public License
Classifier: Operating System :: OS Independent
Classifier: Programming Language :: Python
Classifier: Programming Language :: Python :: 3.7
Classifier: Programming Language :: Python :: 3.8
Classifier: Programming Language :: Python :: 3.9
Classifier: Programming Language :: Python :: 3.10
Classifier: Programming Language :: Python :: 3.11
Classifier: Programming Language :: Python :: Implementation :: CPython
Classifier: Topic :: Internet :: WWW/HTTP :: Site Management
Requires-Python: >=3.7
License-File: LICENSE.txt
Requires-Dist: setuptools
Requires-Dist: plone.portlets
Requires-Dist: zope.component
Requires-Dist: zope.componentvocabulary
Requires-Dist: zope.dottedname
Requires-Dist: zope.interface
Requires-Dist: zope.lifecycleevent
Requires-Dist: zope.pagetemplate
Requires-Dist: zope.schema
Requires-Dist: zope.traversing
Requires-Dist: zope.viewlet
Requires-Dist: Acquisition
Requires-Dist: Zope
Provides-Extra: test
Requires-Dist: plone.testing >=7 ; extra == 'test'
Requires-Dist: zope.publisher ; extra == 'test'
Requires-Dist: zope.site ; extra == 'test'
Requires-Dist: zope.testing ; extra == 'test'
Requires-Dist: transaction ; extra == 'test'
